pyzeus/__init__.py
pyzeus/main.py
pyzeus-0.1.3.dist-info/LICENSE
pyzeus-0.1.3.dist-info/METADATA
pyzeus-0.1.3.dist-info/WHEEL
pyzeus-0.1.3.dist-info/top_level.txt
pyzeus-0.1.3.dist-info/RECORD
