Metadata-Version: 2.1
Name: pyzeus
Version: 0.1.3
Summary: The cors middleware that enables a FastAPI server to handle cors requests, specifically, on the router and individual route level. It also handles preflight requests :)
Home-page: https://github.com/cerebrusinc/pyzeus.git
Author: Lewis Mosho Jr | Cerebrus Inc
Author-email: hello@cerebrus.dev
Project-URL: Bug Tracker, https://github.com/cerebrusinc/pyzeus/issues
Classifier: License :: OSI Approved :: MIT License
Classifier: Programming Language :: Python :: 3
Classifier: Operating System :: OS Independent
Classifier: Topic :: Internet :: WWW/HTTP :: WSGI :: Middleware
Classifier: Development Status :: 5 - Production/Stable
Classifier: Environment :: Plugins
Classifier: Intended Audience :: Developers
Classifier: Typing :: Typed
Requires-Python: >=3.0
License-File: LICENSE
Requires-Dist: fastapi
